Metadata-Version: 2.2
Name: hors-python-partial
Version: 0.1.6
Summary: Разбор дат в строке. Порт на Python проекта https://github.com/DenisNP/Hors с изменениями под неопределённые даты
Home-page: https://github.com/AndrewOch/hors-python-partial
Author: Владимир Шомин
Author-email: 22c.proxima@gmail.com
Maintainer: Андрей Неманов
Maintainer-email: vigvamcev.media@gmail.com
License: MIT
Platform: any
Classifier: Development Status :: 5 - Production/Stable
Classifier: Environment :: Console
Classifier: Intended Audience :: Developers
Classifier: License :: OSI Approved :: MIT License
Classifier: Operating System :: OS Independent
Classifier: Programming Language :: Python
Classifier: Programming Language :: Python :: 3
Classifier: Programming Language :: Python :: 3 :: Only
Classifier: Programming Language :: Python :: 3.7
Classifier: Programming Language :: Python :: 3.8
Classifier: Programming Language :: Python :: 3.9
Classifier: Programming Language :: Python :: 3.10
Classifier: Topic :: Office/Business
Classifier: Topic :: Software Development :: Libraries
Classifier: Topic :: Software Development :: Libraries :: Python Modules
Classifier: Topic :: Software Development :: User Interfaces
Classifier: Topic :: Utilities
Requires-Python: >=3.7
License-File: LICENSE
